pyhomeworksqs/__init__.py
pyhomeworksqs/pyhomeworksqs.py
pyhomeworksqs-0.0.1.dist-info/LICENSE
pyhomeworksqs-0.0.1.dist-info/METADATA
pyhomeworksqs-0.0.1.dist-info/WHEEL
pyhomeworksqs-0.0.1.dist-info/top_level.txt
pyhomeworksqs-0.0.1.dist-info/RECORD
