Metadata-Version: 2.1
Name: pyhomeworksqs
Version: 0.0.1
Summary: Lutron Homeworks QS interface over telnet
Home-page: https://github.com/rverstappen/pyhomeworksqs
Author: Ron Verstappen
Author-email: ronverstappen@esample.com
License: UNKNOWN
Platform: UNKNOWN
Classifier: Programming Language :: Python :: 3
Classifier: License :: OSI Approved :: MIT License
Classifier: Operating System :: OS Independent
License-File: LICENSE
